pynetcraftcli/__init__.py
pynetcraftcli/pynetcraftcli.py
pynetcraftcli/requirements.txt
pynetcraftcli-1.3.dist-info/METADATA
pynetcraftcli-1.3.dist-info/WHEEL
pynetcraftcli-1.3.dist-info/entry_points.txt
pynetcraftcli-1.3.dist-info/top_level.txt
pynetcraftcli-1.3.dist-info/RECORD
