Metadata-Version: 2.4
Name: pynetcraftcli
Version: 1.3
Summary: A simple Python script to interact with Netcraft APIs from CLI
Author-email: tdebize@mail.com
License-Expression: LGPL-3.0-or-later
Project-URL: Homepage, https://github.com/maaaaz/pynetcraftcli
Keywords: netcraft,api,cli,malware,phishing
Classifier: Topic :: Security
Classifier: Programming Language :: Python :: 3
Requires-Python: >=3
Requires-Dist: requests
Requires-Dist: w3lib
Requires-Dist: validators
Requires-Dist: jmespath
